calculatorsamd/__init__.py
calculatorsamd-0.1.dist-info/LICENCE.txt
calculatorsamd-0.1.dist-info/METADATA
calculatorsamd-0.1.dist-info/WHEEL
calculatorsamd-0.1.dist-info/top_level.txt
calculatorsamd-0.1.dist-info/RECORD
