Metadata-Version: 2.1
Name: calculatorsamd
Version: 0.1
Summary: very basic calculator
Home-page: UNKNOWN
Author: Aadil Nazir
Author-email: daraadi4@gmail.com
License: UNKNOWN
Platform: UNKNOWN
Classifier: Programming Language :: Python :: 3
Classifier: License :: OSI Approved :: MIT License
Classifier: Operating System :: OS Independent
